upgrade_tool/__init__.py
upgrade_tool/main.py
upgrade_tool/utils.py
ultimate_python_upgrader-1.4.0.dist-info/METADATA
ultimate_python_upgrader-1.4.0.dist-info/WHEEL
ultimate_python_upgrader-1.4.0.dist-info/entry_points.txt
ultimate_python_upgrader-1.4.0.dist-info/licenses/LICENSE
ultimate_python_upgrader-1.4.0.dist-info/RECORD
