Metadata-Version: 2.4
Name: ultimate-python-upgrader
Version: 1.4.0
Summary: An intelligent CLI tool to upgrade Python packages with dependency analysis and automatic rollback on failure.
Project-URL: Homepage, https://github.com/psywarrior1998/upgrade_all_python
Project-URL: Bug Tracker, https://github.com/psywarrior1998/upgrade_all_python/issues
Author-email: Sanyam Sanjay Sharma <infta2020+pypi@gmail.com>
License: MIT License
License-File: LICENSE
Classifier: Environment :: Console
Classifier: License :: OSI Approved :: MIT License
Classifier: Operating System :: OS Independent
Classifier: Programming Language :: Python :: 3
Classifier: Topic :: Software Development :: Libraries :: Python Modules
Classifier: Topic :: System :: Software Distribution
Requires-Python: >=3.8
Requires-Dist: rich>=13.0.0
Requires-Dist: typer[all]>=0.9.0
Provides-Extra: dev
Requires-Dist: black>=24.4.0; extra == 'dev'
Requires-Dist: build>=1.2.0; extra == 'dev'
Requires-Dist: ruff>=0.4.0; extra == 'dev'
Requires-Dist: twine>=5.1.0; extra == 'dev'
Provides-Extra: test
Requires-Dist: pytest-cov>=4.0.0; extra == 'test'
Requires-Dist: pytest>=8.0.0; extra == 'test'
